pydantic_parser_pool/__init__.py
pydantic_parser_pool/main.py
pydantic_parser_pool-0.1.dist-info/METADATA
pydantic_parser_pool-0.1.dist-info/WHEEL
pydantic_parser_pool-0.1.dist-info/top_level.txt
pydantic_parser_pool-0.1.dist-info/RECORD
