Metadata-Version: 2.1
Name: pydantic_parser_pool
Version: 0.1
Requires-Dist: langchain==0.2.14
